[
    {
        "Requirement_ID":"Req001",
        "Content":"TCU shall turn ON when driver turn ON KL30 & KL15, and TCU shall turn OFF when driver turn OFF KL30 or KL15. ",
        "Header":"Clamp control ",
        "Qualification_Method":"TCU or Modem supplier is responsible for providing the test result to Brand for approval",
        "Artifact_Type":"System Requirement",
        "System_Requirement_State":"Approved",
        "Assignee":"ABC",
        "Review_Comment":"None",
        "Primary_Discipline":"HW-SW",
        "Requirement_Type":"System",
        "System_Elements":"Clamp control",
        "ASIL_Rating":"A",
        "Cybersecurity":false,
        "Key_Requirement":true,
        "Legal_Certification_Requirement":null,
        "Variant":"XYZ_Model_2025",
        "Verification_Method":"H\/W Integration",
        "Verification_Owner":"Modem Funcational team"
    },
    {
        "Requirement_ID":"Req002",
        "Content":"TCU shall start searching for corresponding eNodeB cells when KL30 & KL15 is ON",
        "Header":"Network selection",
        "Qualification_Method":"TCU or Momdem Connectivity team supplier is responsible for providing the test result to Brand for approval",
        "Artifact_Type":"System Requirement",
        "System_Requirement_State":"Approved",
        "Assignee":"XYZ",
        "Review_Comment":"None",
        "Primary_Discipline":"HW-SW",
        "Requirement_Type":"System",
        "System_Elements":"Clamp control",
        "ASIL_Rating":"A",
        "Cybersecurity":false,
        "Key_Requirement":true,
        "Legal_Certification_Requirement":null,
        "Variant":"XYZ_Model_2025",
        "Verification_Method":"H\/W Integration",
        "Verification_Owner":"Modem Funcational team"
    },
    {
        "Requirement_ID":"Req003",
        "Content":"TCU shall operate on default bootstrap profile when the device is roaming it in the home country",
        "Header":"Network selection",
        "Qualification_Method":"Connectivity team supplier is responsible for providing the test result to Brand for approval",
        "Artifact_Type":"Functional Requirement",
        "System_Requirement_State":"Approved",
        "Assignee":"XYZ",
        "Review_Comment":"None",
        "Primary_Discipline":"SW",
        "Requirement_Type":"Functional",
        "System_Elements":"Connectivity",
        "ASIL_Rating":"A",
        "Cybersecurity":true,
        "Key_Requirement":true,
        "Legal_Certification_Requirement":true,
        "Variant":"XYZ_Model_2025",
        "Verification_Method":"SIT",
        "Verification_Owner":"Connecitivity Team"
    },
    {
        "Requirement_ID":"Req004",
        "Content":"TCU should perform network registration to the primary MNO based on the current profile on the eSIM",
        "Header":"Network selection",
        "Qualification_Method":"Connectivity team supplier is responsible for providing the test result to Brand for approval",
        "Artifact_Type":"Functional Requirement",
        "System_Requirement_State":"Approved",
        "Assignee":"XYZ",
        "Review_Comment":"None",
        "Primary_Discipline":"SW",
        "Requirement_Type":"Functional",
        "System_Elements":"Connectivity",
        "ASIL_Rating":"A",
        "Cybersecurity":true,
        "Key_Requirement":true,
        "Legal_Certification_Requirement":true,
        "Variant":"XYZ_Model_2025",
        "Verification_Method":"SIT",
        "Verification_Owner":"Connecitivity Team"
    },
    {
        "Requirement_ID":"Req005",
        "Content":"TCU should attached to it primary network based on MCC\/MNC combination of it IMSI ",
        "Header":"Network selection",
        "Qualification_Method":"Connectivity team supplier is responsible for providing the test result to Brand for approval",
        "Artifact_Type":"Functional Requirement",
        "System_Requirement_State":"Approved",
        "Assignee":"XYZ",
        "Review_Comment":"None",
        "Primary_Discipline":"SW",
        "Requirement_Type":"Functional",
        "System_Elements":"Connectivity",
        "ASIL_Rating":"A",
        "Cybersecurity":true,
        "Key_Requirement":true,
        "Legal_Certification_Requirement":true,
        "Variant":"XYZ_Model_2025",
        "Verification_Method":"SIT",
        "Verification_Owner":"Connecitivity Team"
    },
    {
        "Requirement_ID":"Req006",
        "Content":"TCU shall perform Operation profile download when the device is roaming in the foreign country also depending on the OEM and MNO contracts.",
        "Header":"Network selection",
        "Qualification_Method":"Connectivity team supplier is responsible for providing the test result to Brand for approval",
        "Artifact_Type":"Functional Requirement",
        "System_Requirement_State":"Approved",
        "Assignee":"XYZ",
        "Review_Comment":"None",
        "Primary_Discipline":"SW",
        "Requirement_Type":"Functional",
        "System_Elements":"Connectivity",
        "ASIL_Rating":"A",
        "Cybersecurity":true,
        "Key_Requirement":true,
        "Legal_Certification_Requirement":true,
        "Variant":"XYZ_Model_2025",
        "Verification_Method":"SIT",
        "Verification_Owner":"Connecitivity Team"
    },
    {
        "Requirement_ID":"Req007",
        "Content":"TCU shall start searching for corresponding eNodeB cells when KL30 & KL15 is ON",
        "Header":"Network selection",
        "Qualification_Method":"TCU or Momdem Connectivity team supplier is responsible for providing the test result to Brand for approval",
        "Artifact_Type":"System Requirement",
        "System_Requirement_State":"Approved",
        "Assignee":"XYZ",
        "Review_Comment":"None",
        "Primary_Discipline":"HW-SW",
        "Requirement_Type":"System",
        "System_Elements":"Clamp control",
        "ASIL_Rating":"A",
        "Cybersecurity":false,
        "Key_Requirement":true,
        "Legal_Certification_Requirement":null,
        "Variant":"XYZ_Model_2025",
        "Verification_Method":"H\/W Integration",
        "Verification_Owner":"Modem Funcational team"
    },
    {
        "Requirement_ID":"Req008",
        "Content":"TCU shall operate on default bootstrap profile when the device is roaming it in the home country",
        "Header":"Network selection",
        "Qualification_Method":"Connectivity team supplier is responsible for providing the test result to Brand for approval",
        "Artifact_Type":"Functional Requirement",
        "System_Requirement_State":"Approved",
        "Assignee":"XYZ",
        "Review_Comment":"None",
        "Primary_Discipline":"SW",
        "Requirement_Type":"Functional",
        "System_Elements":"Connectivity",
        "ASIL_Rating":"A",
        "Cybersecurity":true,
        "Key_Requirement":true,
        "Legal_Certification_Requirement":true,
        "Variant":"XYZ_Model_2025",
        "Verification_Method":"SIT",
        "Verification_Owner":"Connecitivity Team"
    },
    {
        "Requirement_ID":"Req009",
        "Content":"TCU should perform network registration to the primary MNO based on the current profile on the eSIM",
        "Header":"Network selection",
        "Qualification_Method":"Connectivity team supplier is responsible for providing the test result to Brand for approval",
        "Artifact_Type":"Functional Requirement",
        "System_Requirement_State":"Approved",
        "Assignee":"XYZ",
        "Review_Comment":"None",
        "Primary_Discipline":"SW",
        "Requirement_Type":"Functional",
        "System_Elements":"Connectivity",
        "ASIL_Rating":"A",
        "Cybersecurity":true,
        "Key_Requirement":true,
        "Legal_Certification_Requirement":true,
        "Variant":"XYZ_Model_2025",
        "Verification_Method":"SIT",
        "Verification_Owner":"Connecitivity Team"
    },
    {
        "Requirement_ID":"Req010",
        "Content":"TCU should attached to it primary network based on MCC\/MNC combination of it IMSI ",
        "Header":"Network selection",
        "Qualification_Method":"Connectivity team supplier is responsible for providing the test result to Brand for approval",
        "Artifact_Type":"Functional Requirement",
        "System_Requirement_State":"Approved",
        "Assignee":"XYZ",
        "Review_Comment":"None",
        "Primary_Discipline":"SW",
        "Requirement_Type":"Functional",
        "System_Elements":"Connectivity",
        "ASIL_Rating":"A",
        "Cybersecurity":true,
        "Key_Requirement":true,
        "Legal_Certification_Requirement":true,
        "Variant":"XYZ_Model_2025",
        "Verification_Method":"SIT",
        "Verification_Owner":"Connecitivity Team"
    },
    {
        "Requirement_ID":"Req011",
        "Content":"TCU shall perform Operation profile download when the device is roaming in the foreign country also depending on the OEM and MNO contracts.",
        "Header":"Network selection",
        "Qualification_Method":"Connectivity team supplier is responsible for providing the test result to Brand for approval",
        "Artifact_Type":"Functional Requirement",
        "System_Requirement_State":"Approved",
        "Assignee":"XYZ",
        "Review_Comment":"None",
        "Primary_Discipline":"SW",
        "Requirement_Type":"Functional",
        "System_Elements":"Connectivity",
        "ASIL_Rating":"A",
        "Cybersecurity":true,
        "Key_Requirement":true,
        "Legal_Certification_Requirement":true,
        "Variant":"XYZ_Model_2025",
        "Verification_Method":"SIT",
        "Verification_Owner":"Connecitivity Team"
    },
    {
        "Requirement_ID":"Req012",
        "Content":"TCU shall send a PDN Connection to the network to register APNs",
        "Header":"Network registration",
        "Qualification_Method":"Connectivity team supplier is responsible for providing the test result to Brand for approval",
        "Artifact_Type":"Functional Requirement",
        "System_Requirement_State":"Approved",
        "Assignee":"XYZ",
        "Review_Comment":"None",
        "Primary_Discipline":"SW",
        "Requirement_Type":"Functional",
        "System_Elements":"Connectivity",
        "ASIL_Rating":"A",
        "Cybersecurity":true,
        "Key_Requirement":true,
        "Legal_Certification_Requirement":true,
        "Variant":"XYZ_Model_2025",
        "Verification_Method":"SIT",
        "Verification_Owner":"Connecitivity Team"
    },
    {
        "Requirement_ID":"Req013",
        "Content":"TCU shall be VoLTE capable when registered to LTE or higher RATs if IMS registration is successful.",
        "Header":"Network registration",
        "Qualification_Method":"Connectivity team supplier is responsible for providing the test result to Brand for approval",
        "Artifact_Type":"Functional Requirement",
        "System_Requirement_State":"Approved",
        "Assignee":"XYZ",
        "Review_Comment":"None",
        "Primary_Discipline":"SW",
        "Requirement_Type":"Functional",
        "System_Elements":"Connectivity",
        "ASIL_Rating":"A",
        "Cybersecurity":true,
        "Key_Requirement":true,
        "Legal_Certification_Requirement":true,
        "Variant":"XYZ_Model_2025",
        "Verification_Method":"SIT",
        "Verification_Owner":"Connecitivity Team"
    },
    {
        "Requirement_ID":"Req014",
        "Content":"TCU may be configured with eCall only mode based on the vehicle configuration i.e. TCU perform network registration when eCall is triggered",
        "Header":"TCU configuration",
        "Qualification_Method":"Connectivity team supplier is responsible for providing the test result to Brand for approval",
        "Artifact_Type":"Functional Requirement",
        "System_Requirement_State":"Approved",
        "Assignee":"XYZ",
        "Review_Comment":"None",
        "Primary_Discipline":"SW",
        "Requirement_Type":"Functional",
        "System_Elements":"Connectivity",
        "ASIL_Rating":"A",
        "Cybersecurity":true,
        "Key_Requirement":true,
        "Legal_Certification_Requirement":true,
        "Variant":"XYZ_Model_2025",
        "Verification_Method":"SIT",
        "Verification_Owner":"Connecitivity Team"
    },
    {
        "Requirement_ID":"Req015",
        "Content":"TCU shall receive corrrect GPS location information i.e. correct latitude and longitute from the GNSS driver",
        "Header":"TCU configuration",
        "Qualification_Method":"Connectivity team supplier is responsible for providing the test result to Brand for approval",
        "Artifact_Type":"Functional Requirement",
        "System_Requirement_State":"Approved",
        "Assignee":"XYZ",
        "Review_Comment":"None",
        "Primary_Discipline":"HW-SW",
        "Requirement_Type":"Functional",
        "System_Elements":"Connectivity",
        "ASIL_Rating":"A",
        "Cybersecurity":true,
        "Key_Requirement":true,
        "Legal_Certification_Requirement":true,
        "Variant":"XYZ_Model_2025",
        "Verification_Method":"SIT",
        "Verification_Owner":"Connecitivity Team"
    },
    {
        "Requirement_ID":"Req016",
        "Content":"TCU or vehicle shall be equippied with eCall service regardless of whether or not a vehicle owner opts for a TPS eCall service",
        "Header":"TCU configuration",
        "Qualification_Method":"eCall team supplier is responsible for providing the test result to Brand for approval",
        "Artifact_Type":"Functional Requirement",
        "System_Requirement_State":"Approved",
        "Assignee":"PQRS",
        "Review_Comment":"None",
        "Primary_Discipline":"SW",
        "Requirement_Type":"Functional",
        "System_Elements":"eCall",
        "ASIL_Rating":"A",
        "Cybersecurity":true,
        "Key_Requirement":true,
        "Legal_Certification_Requirement":true,
        "Variant":"XYZ_Model_2025",
        "Verification_Method":"SIT",
        "Verification_Owner":"eCall Funcational Team"
    },
    {
        "Requirement_ID":"Req017",
        "Content":"TCU shall receive eCall dataset from eCall Application which initially is received once TCU is online and registered to its OEM server.",
        "Header":"eCall configuration",
        "Qualification_Method":"eCall team supplier is responsible for providing the test result to Brand for approval",
        "Artifact_Type":"Functional Requirement",
        "System_Requirement_State":"Approved",
        "Assignee":"PQRS",
        "Review_Comment":"None",
        "Primary_Discipline":"SW",
        "Requirement_Type":"Functional",
        "System_Elements":"eCall",
        "ASIL_Rating":"A",
        "Cybersecurity":true,
        "Key_Requirement":true,
        "Legal_Certification_Requirement":false,
        "Variant":"XYZ_Model_2025",
        "Verification_Method":"SIT",
        "Verification_Owner":"eCall Funcational Team"
    },
    {
        "Requirement_ID":"Req018",
        "Content":"TCU shall receive eCall dataset from eCall Application via vehicle disgnostics based on the regional requirements.\n",
        "Header":"eCall configuration",
        "Qualification_Method":"eCall team supplier is responsible for providing the test result to Brand for approval",
        "Artifact_Type":"Functional Requirement",
        "System_Requirement_State":"Approved",
        "Assignee":"PQRS",
        "Review_Comment":"None",
        "Primary_Discipline":"SW",
        "Requirement_Type":"Functional",
        "System_Elements":"eCall",
        "ASIL_Rating":"A",
        "Cybersecurity":true,
        "Key_Requirement":true,
        "Legal_Certification_Requirement":false,
        "Variant":"XYZ_Model_2025",
        "Verification_Method":"SIT",
        "Verification_Owner":"eCall Funcational Team"
    },
    {
        "Requirement_ID":"Req019",
        "Content":"Offline regions or Ecall only regions shall have different ecall number, refer to the MNO configuration table",
        "Header":"eCall configuration",
        "Qualification_Method":"eCall team supplier is responsible for providing the test result to Brand for approval",
        "Artifact_Type":"Functional Requirement",
        "System_Requirement_State":"Approved",
        "Assignee":"PQRS",
        "Review_Comment":"None",
        "Primary_Discipline":"SW",
        "Requirement_Type":"Functional",
        "System_Elements":"eCall",
        "ASIL_Rating":"A",
        "Cybersecurity":true,
        "Key_Requirement":true,
        "Legal_Certification_Requirement":false,
        "Variant":"XYZ_Model_2025",
        "Verification_Method":"SIT",
        "Verification_Owner":"eCall Funcational Team"
    },
    {
        "Requirement_ID":"Req020",
        "Content":"ECall dataset shall include the type of ecall i.e. TPS or EU Ecall; Ecall Numbers, T9 & T10 timers.",
        "Header":"eCall configuration",
        "Qualification_Method":"eCall team supplier is responsible for providing the test result to Brand for approval",
        "Artifact_Type":"Functional Requirement",
        "System_Requirement_State":"Approved",
        "Assignee":"PQRS",
        "Review_Comment":"None",
        "Primary_Discipline":"SW",
        "Requirement_Type":"Functional",
        "System_Elements":"eCall",
        "ASIL_Rating":"A",
        "Cybersecurity":true,
        "Key_Requirement":true,
        "Legal_Certification_Requirement":false,
        "Variant":"XYZ_Model_2025",
        "Verification_Method":"SIT",
        "Verification_Owner":"eCall Funcational Team"
    },
    {
        "Requirement_ID":"Req021",
        "Content":"TCU shall be able to trigger manual EU eCall or Private Ecall when TCU is registered in any RAT i.e. GMS\/UMTS\/LTE\/5G-NSA\/5G-SA.",
        "Header":"eCall configuration",
        "Qualification_Method":"eCall team supplier is responsible for providing the test result to Brand for approval",
        "Artifact_Type":"Functional Requirement",
        "System_Requirement_State":"Approved",
        "Assignee":"PQRS",
        "Review_Comment":"None",
        "Primary_Discipline":"HW-SW",
        "Requirement_Type":"Functional",
        "System_Elements":"eCall",
        "ASIL_Rating":"A",
        "Cybersecurity":true,
        "Key_Requirement":true,
        "Legal_Certification_Requirement":true,
        "Variant":"XYZ_Model_2025",
        "Verification_Method":"SIT",
        "Verification_Owner":"eCall Funcational Team"
    },
    {
        "Requirement_ID":"Req022",
        "Content":"TCU shall be able to trigger TPS (Private ECall)\/EU eCall automatically when Airbags are initated when unit is registered in any RAT i.e. GMS\/UMTS\/LTE\/5G-NSA\/5G-SA.",
        "Header":"eCall configuration",
        "Qualification_Method":"eCall team supplier is responsible for providing the test result to Brand for approval",
        "Artifact_Type":"Functional Requirement",
        "System_Requirement_State":"Approved",
        "Assignee":"PQRS",
        "Review_Comment":"None",
        "Primary_Discipline":"HW-SW",
        "Requirement_Type":"Functional",
        "System_Elements":"eCall",
        "ASIL_Rating":"A",
        "Cybersecurity":true,
        "Key_Requirement":true,
        "Legal_Certification_Requirement":true,
        "Variant":"XYZ_Model_2025",
        "Verification_Method":"SIT",
        "Verification_Owner":"eCall Funcational Team"
    },
    {
        "Requirement_ID":"Req023",
        "Content":"TCU shall be able to trigger manual TPS (Third Part Service or Private ECall) eCall when TCU is registered in any RAT i.e. GMS\/UMTS\/LTE\/5G-NSA\/5G-SA.",
        "Header":"eCall configuration",
        "Qualification_Method":"eCall team supplier is responsible for providing the test result to Brand for approval",
        "Artifact_Type":"Functional Requirement",
        "System_Requirement_State":"Approved",
        "Assignee":"PQRS",
        "Review_Comment":"None",
        "Primary_Discipline":"HW-SW",
        "Requirement_Type":"Functional",
        "System_Elements":"eCall",
        "ASIL_Rating":"A",
        "Cybersecurity":true,
        "Key_Requirement":true,
        "Legal_Certification_Requirement":true,
        "Variant":"XYZ_Model_2025",
        "Verification_Method":"SIT",
        "Verification_Owner":"eCall Funcational Team"
    },
    {
        "Requirement_ID":"Req024",
        "Content":"TCU shall be cable to trigger automatic TPS (Third Part Service or Private ECall) eCall when TCU is registered in any RAT i.e. GMS\/UMTS\/LTE\/5G-NSA\/5G-SA.",
        "Header":"eCall configuration",
        "Qualification_Method":"eCall team supplier is responsible for providing the test result to Brand for approval",
        "Artifact_Type":"Functional Requirement",
        "System_Requirement_State":"Approved",
        "Assignee":"PQRS",
        "Review_Comment":"None",
        "Primary_Discipline":"HW-SW",
        "Requirement_Type":"Functional",
        "System_Elements":"eCall",
        "ASIL_Rating":"A",
        "Cybersecurity":true,
        "Key_Requirement":true,
        "Legal_Certification_Requirement":true,
        "Variant":"XYZ_Model_2025",
        "Verification_Method":"SIT",
        "Verification_Owner":"eCall Funcational Team"
    },
    {
        "Requirement_ID":"Req025",
        "Content":"TCU shall be able to trigger manual TPS (Third Part Service) eCall when TCU is registered in VoLTE in case of Private Ecall.",
        "Header":"eCall configuration",
        "Qualification_Method":"eCall team supplier is responsible for providing the test result to Brand for approval",
        "Artifact_Type":"Functional Requirement",
        "System_Requirement_State":"Approved",
        "Assignee":"PQRS",
        "Review_Comment":"None",
        "Primary_Discipline":"HW-SW",
        "Requirement_Type":"Functional",
        "System_Elements":"eCall",
        "ASIL_Rating":"A",
        "Cybersecurity":true,
        "Key_Requirement":true,
        "Legal_Certification_Requirement":true,
        "Variant":"XYZ_Model_2025",
        "Verification_Method":"SIT",
        "Verification_Owner":"eCall Funcational Team"
    },
    {
        "Requirement_ID":"Req026",
        "Content":"TCU shall be cable to trigger automatic TPS (Third Part Service) eCall when TCU is registered in VoLTE  in case of Private Ecall.",
        "Header":"eCall configuration",
        "Qualification_Method":"eCall team supplier is responsible for providing the test result to Brand for approval",
        "Artifact_Type":"Functional Requirement",
        "System_Requirement_State":"Approved",
        "Assignee":"PQRS",
        "Review_Comment":"None",
        "Primary_Discipline":"HW-SW",
        "Requirement_Type":"Functional",
        "System_Elements":"eCall",
        "ASIL_Rating":"A",
        "Cybersecurity":true,
        "Key_Requirement":true,
        "Legal_Certification_Requirement":true,
        "Variant":"XYZ_Model_2025",
        "Verification_Method":"SIT",
        "Verification_Owner":"eCall Funcational Team"
    },
    {
        "Requirement_ID":"Req027",
        "Content":"TCU shall be perform CSFB when EU ecall is triggered in LTE or higher RATs.",
        "Header":"eCall configuration",
        "Qualification_Method":"eCall team supplier is responsible for providing the test result to Brand for approval",
        "Artifact_Type":"Functional Requirement",
        "System_Requirement_State":"Approved",
        "Assignee":"PQRS",
        "Review_Comment":"None",
        "Primary_Discipline":"SW",
        "Requirement_Type":"Functional",
        "System_Elements":"eCall",
        "ASIL_Rating":"A",
        "Cybersecurity":true,
        "Key_Requirement":true,
        "Legal_Certification_Requirement":true,
        "Variant":"XYZ_Model_2025",
        "Verification_Method":"SIT",
        "Verification_Owner":"eCall Funcational Team"
    },
    {
        "Requirement_ID":"Req028",
        "Content":"Two-way voice communication shall be established between the IVS (In-Vehicle System) and the PSAP in case of EU Ecall.",
        "Header":"MO eCall",
        "Qualification_Method":"eCall team supplier is responsible for providing the test result to Brand for approval",
        "Artifact_Type":"Functional Requirement",
        "System_Requirement_State":"Approved",
        "Assignee":"PQRS",
        "Review_Comment":"None",
        "Primary_Discipline":"SW",
        "Requirement_Type":"Functional",
        "System_Elements":"eCall",
        "ASIL_Rating":"A",
        "Cybersecurity":true,
        "Key_Requirement":true,
        "Legal_Certification_Requirement":true,
        "Variant":"XYZ_Model_2025",
        "Verification_Method":"SIT",
        "Verification_Owner":"eCall Funcational Team"
    },
    {
        "Requirement_ID":"Req029",
        "Content":"Two-way voice communication shall be established between the IVS (In-Vehicle System) and TSP (Third Part Service) in case Private ECall. ",
        "Header":"MO eCall",
        "Qualification_Method":"eCall team supplier is responsible for providing the test result to Brand for approval",
        "Artifact_Type":"Functional Requirement",
        "System_Requirement_State":"Approved",
        "Assignee":"PQRS",
        "Review_Comment":"None",
        "Primary_Discipline":"SW",
        "Requirement_Type":"Functional",
        "System_Elements":"eCall",
        "ASIL_Rating":"A",
        "Cybersecurity":true,
        "Key_Requirement":true,
        "Legal_Certification_Requirement":true,
        "Variant":"XYZ_Model_2025",
        "Verification_Method":"SIT",
        "Verification_Owner":"eCall Funcational Team"
    },
    {
        "Requirement_ID":"Req030",
        "Content":"The quality of voice communication shall be verified by validation team in all RATs in case of MO call.",
        "Header":"MO eCall",
        "Qualification_Method":"eCall team supplier is responsible for providing the test result to Brand for approval",
        "Artifact_Type":"Functional Requirement",
        "System_Requirement_State":"Approved",
        "Assignee":"PQRS",
        "Review_Comment":"None",
        "Primary_Discipline":"SW",
        "Requirement_Type":"Functional",
        "System_Elements":"eCall",
        "ASIL_Rating":"A",
        "Cybersecurity":true,
        "Key_Requirement":true,
        "Legal_Certification_Requirement":true,
        "Variant":"XYZ_Model_2025",
        "Verification_Method":"SIT",
        "Verification_Owner":"eCall Funcational Team"
    },
    {
        "Requirement_ID":"Req031",
        "Content":"TCU should be able to receive a clear-down eCall request from the PSAP or hang-up the eCall.",
        "Header":"MT eCall",
        "Qualification_Method":"eCall team supplier is responsible for providing the test result to Brand for approval",
        "Artifact_Type":"Functional Requirement",
        "System_Requirement_State":"Approved",
        "Assignee":"PQRS",
        "Review_Comment":"None",
        "Primary_Discipline":"SW",
        "Requirement_Type":"Functional",
        "System_Elements":"eCall",
        "ASIL_Rating":"A",
        "Cybersecurity":true,
        "Key_Requirement":true,
        "Legal_Certification_Requirement":true,
        "Variant":"XYZ_Model_2025",
        "Verification_Method":"SIT",
        "Verification_Owner":"eCall Funcational Team"
    },
    {
        "Requirement_ID":"Req032",
        "Content":"TCU shall receive a call-back from the PSAP in case of EU Ecall.",
        "Header":"MT eCall",
        "Qualification_Method":"eCall team supplier is responsible for providing the test result to Brand for approval",
        "Artifact_Type":"Functional Requirement",
        "System_Requirement_State":"Approved",
        "Assignee":"PQRS",
        "Review_Comment":"None",
        "Primary_Discipline":"SW",
        "Requirement_Type":"Functional",
        "System_Elements":"eCall",
        "ASIL_Rating":"A",
        "Cybersecurity":true,
        "Key_Requirement":true,
        "Legal_Certification_Requirement":true,
        "Variant":"XYZ_Model_2025",
        "Verification_Method":"SIT",
        "Verification_Owner":"eCall Funcational Team"
    },
    {
        "Requirement_ID":"Req033",
        "Content":"TCU shall receive a call-back from the PSAP in case of Private ECall.",
        "Header":"MT eCall",
        "Qualification_Method":"eCall team supplier is responsible for providing the test result to Brand for approval",
        "Artifact_Type":"Functional Requirement",
        "System_Requirement_State":"Approved",
        "Assignee":"PQRS",
        "Review_Comment":"None",
        "Primary_Discipline":"SW",
        "Requirement_Type":"Functional",
        "System_Elements":"eCall",
        "ASIL_Rating":"A",
        "Cybersecurity":true,
        "Key_Requirement":true,
        "Legal_Certification_Requirement":true,
        "Variant":"XYZ_Model_2025",
        "Verification_Method":"SIT",
        "Verification_Owner":"eCall Funcational Team"
    },
    {
        "Requirement_ID":"Req043",
        "Content":"The quality of voice communication shall be verified by validation team in all RATs in case of MT call.",
        "Header":"MT eCall",
        "Qualification_Method":"eCall team supplier is responsible for providing the test result to Brand for approval",
        "Artifact_Type":"Functional Requirement",
        "System_Requirement_State":"Approved",
        "Assignee":"PQRS",
        "Review_Comment":"None",
        "Primary_Discipline":"SW",
        "Requirement_Type":"Functional",
        "System_Elements":"eCall",
        "ASIL_Rating":"A",
        "Cybersecurity":true,
        "Key_Requirement":true,
        "Legal_Certification_Requirement":true,
        "Variant":"XYZ_Model_2025",
        "Verification_Method":"SIT",
        "Verification_Owner":"eCall Funcational Team"
    },
    {
        "Requirement_ID":"Req034",
        "Content":"TCU shall send MSD (Minimum Set Data) via SMS when an eCall is triggered in all RATs",
        "Header":"MSD Transmission",
        "Qualification_Method":"eCall team supplier is responsible for providing the test result to Brand for approval",
        "Artifact_Type":"Functional Requirement",
        "System_Requirement_State":"Approved",
        "Assignee":"PQRS",
        "Review_Comment":"None",
        "Primary_Discipline":"SW",
        "Requirement_Type":"Functional",
        "System_Elements":"eCall",
        "ASIL_Rating":"A",
        "Cybersecurity":true,
        "Key_Requirement":true,
        "Legal_Certification_Requirement":true,
        "Variant":"XYZ_Model_2025",
        "Verification_Method":"SIT",
        "Verification_Owner":"eCall Funcational Team"
    },
    {
        "Requirement_ID":"Req035",
        "Content":"TCU shall send MSD (Minimum Set Data) via SMS and SIP when an TPS eCall is triggered in LTE or higher RATs.",
        "Header":"MSD Transmission",
        "Qualification_Method":"eCall team supplier is responsible for providing the test result to Brand for approval",
        "Artifact_Type":"Functional Requirement",
        "System_Requirement_State":"Approved",
        "Assignee":"PQRS",
        "Review_Comment":"None",
        "Primary_Discipline":"SW",
        "Requirement_Type":"Functional",
        "System_Elements":"eCall",
        "ASIL_Rating":"A",
        "Cybersecurity":true,
        "Key_Requirement":true,
        "Legal_Certification_Requirement":true,
        "Variant":"XYZ_Model_2025",
        "Verification_Method":"SIT",
        "Verification_Owner":"eCall Funcational Team"
    },
    {
        "Requirement_ID":"Req036",
        "Content":"MSD data tranmistted via SMS or SIP shall contain VIN, color of the vehicle, GPS Location (latitute\/Longitute), total number of Passengers in  Vehicle",
        "Header":"MSD Transmission",
        "Qualification_Method":"eCall team supplier is responsible for providing the test result to Brand for approval",
        "Artifact_Type":"Functional Requirement",
        "System_Requirement_State":"Approved",
        "Assignee":"PQRS",
        "Review_Comment":"None",
        "Primary_Discipline":"SW",
        "Requirement_Type":"Functional",
        "System_Elements":"eCall",
        "ASIL_Rating":"A",
        "Cybersecurity":true,
        "Key_Requirement":true,
        "Legal_Certification_Requirement":true,
        "Variant":"XYZ_Model_2025",
        "Verification_Method":"SIT",
        "Verification_Owner":"eCall Funcational Team"
    },
    {
        "Requirement_ID":"Req037",
        "Content":"MSD data shall indicate if the activation type of the ecall i.e Manual eCall or Automatic eCall or Test Call",
        "Header":"MSD Transmission",
        "Qualification_Method":"eCall team supplier is responsible for providing the test result to Brand for approval",
        "Artifact_Type":"Functional Requirement",
        "System_Requirement_State":"Approved",
        "Assignee":"PQRS",
        "Review_Comment":"None",
        "Primary_Discipline":"SW",
        "Requirement_Type":"Functional",
        "System_Elements":"eCall",
        "ASIL_Rating":"A",
        "Cybersecurity":true,
        "Key_Requirement":true,
        "Legal_Certification_Requirement":true,
        "Variant":"XYZ_Model_2025",
        "Verification_Method":"SIT",
        "Verification_Owner":"eCall Funcational Team"
    },
    {
        "Requirement_ID":"Req038",
        "Content":"TCU Unit shall received a MSD retransmission request from the PSAP or TPS to update MSD information. This requirement should be applicable for initial eCall trigger and call-back from PSAP\/TSP.",
        "Header":"MSD Transmission",
        "Qualification_Method":"eCall team supplier is responsible for providing the test result to Brand for approval",
        "Artifact_Type":"Functional Requirement",
        "System_Requirement_State":"Approved",
        "Assignee":"PQRS",
        "Review_Comment":"None",
        "Primary_Discipline":"SW",
        "Requirement_Type":"Functional",
        "System_Elements":"eCall",
        "ASIL_Rating":"A",
        "Cybersecurity":true,
        "Key_Requirement":true,
        "Legal_Certification_Requirement":true,
        "Variant":"XYZ_Model_2025",
        "Verification_Method":"SIT",
        "Verification_Owner":"eCall Funcational Team"
    },
    {
        "Requirement_ID":"Req039",
        "Content":"TCU shall enter the wait callback state when initial eCall session is ended in case of accident or passenger in the vehicle cannot reach the agent. ",
        "Header":"Callback eCall",
        "Qualification_Method":"eCall team supplier is responsible for providing the test result to Brand for approval",
        "Artifact_Type":"Functional Requirement",
        "System_Requirement_State":"Approved",
        "Assignee":"PQRS",
        "Review_Comment":"None",
        "Primary_Discipline":"SW",
        "Requirement_Type":"Functional",
        "System_Elements":"eCall",
        "ASIL_Rating":"A",
        "Cybersecurity":true,
        "Key_Requirement":true,
        "Legal_Certification_Requirement":true,
        "Variant":"XYZ_Model_2025",
        "Verification_Method":"SIT",
        "Verification_Owner":"eCall Funcational Team"
    },
    {
        "Requirement_ID":"Req040",
        "Content":"TCU shall perform automatic redials if the initial call set-up attempt fails due to busy, network congestion or PSAP out-of-service.",
        "Header":"Redials scenario",
        "Qualification_Method":"eCall team supplier is responsible for providing the test result to Brand for approval",
        "Artifact_Type":"Functional Requirement",
        "System_Requirement_State":"Approved",
        "Assignee":"PQRS",
        "Review_Comment":"None",
        "Primary_Discipline":"SW",
        "Requirement_Type":"Functional",
        "System_Elements":"eCall",
        "ASIL_Rating":"A",
        "Cybersecurity":true,
        "Key_Requirement":true,
        "Legal_Certification_Requirement":true,
        "Variant":"XYZ_Model_2025",
        "Verification_Method":"SIT",
        "Verification_Owner":"eCall Funcational Team"
    },
    {
        "Requirement_ID":"Req041",
        "Content":"TCU shall perform automatic redials if the initial call set-up attempt fails due no answer. This can be verified with audio monitor that vehicle received \"ring-back tone\". In this case automatic redials attempts should be completed within 2 miutes as defined in ETSI EN 16072 [5]",
        "Header":"Redials scenario",
        "Qualification_Method":"eCall team supplier is responsible for providing the test result to Brand for approval",
        "Artifact_Type":"Functional Requirement",
        "System_Requirement_State":"Approved",
        "Assignee":"PQRS",
        "Review_Comment":"None",
        "Primary_Discipline":"SW",
        "Requirement_Type":"Functional",
        "System_Elements":"eCall",
        "ASIL_Rating":"A",
        "Cybersecurity":true,
        "Key_Requirement":true,
        "Legal_Certification_Requirement":true,
        "Variant":"XYZ_Model_2025",
        "Verification_Method":"SIT",
        "Verification_Owner":"eCall Funcational Team"
    },
    {
        "Requirement_ID":"Req042",
        "Content":"Two-way voice communication shall be established between  IVS (In-Vehicle System) and the PSAP or TSP after MSD retranmission.  This requirement should be applicable for initial eCall trigger and call-back from PSAP\/TSP.",
        "Header":"eCall Generic",
        "Qualification_Method":"eCall team supplier is responsible for providing the test result to Brand for approval",
        "Artifact_Type":"Functional Requirement",
        "System_Requirement_State":"Approved",
        "Assignee":"PQRS",
        "Review_Comment":"None",
        "Primary_Discipline":"SW",
        "Requirement_Type":"Functional",
        "System_Elements":"eCall",
        "ASIL_Rating":"A",
        "Cybersecurity":true,
        "Key_Requirement":true,
        "Legal_Certification_Requirement":true,
        "Variant":"XYZ_Model_2025",
        "Verification_Method":"SIT",
        "Verification_Owner":"eCall Funcational Team"
    },
    {
        "Requirement_ID":"Req043",
        "Content":"TCU shall have only one active eCall service at a time i.e. either TSP or EU ecall is activate and other is deactivated. ",
        "Header":"eCall Generic",
        "Qualification_Method":"eCall team supplier is responsible for providing the test result to Brand for approval",
        "Artifact_Type":"Functional Requirement",
        "System_Requirement_State":"Approved",
        "Assignee":"PQRS",
        "Review_Comment":"None",
        "Primary_Discipline":"SW",
        "Requirement_Type":"Functional",
        "System_Elements":"eCall",
        "ASIL_Rating":"A",
        "Cybersecurity":true,
        "Key_Requirement":true,
        "Legal_Certification_Requirement":true,
        "Variant":"XYZ_Model_2025",
        "Verification_Method":"SIT",
        "Verification_Owner":"eCall Funcational Team"
    },
    {
        "Requirement_ID":"Req044",
        "Content":"TCU shall fallback to EU ecall when TSP is not functional or the TSP cannot be reached due to unavailablitiy of the service in that region or market.",
        "Header":"eCall Generic",
        "Qualification_Method":"eCall team supplier is responsible for providing the test result to Brand for approval",
        "Artifact_Type":"Functional Requirement",
        "System_Requirement_State":"Approved",
        "Assignee":"PQRS",
        "Review_Comment":"None",
        "Primary_Discipline":"SW",
        "Requirement_Type":"Functional",
        "System_Elements":"eCall",
        "ASIL_Rating":"A",
        "Cybersecurity":true,
        "Key_Requirement":true,
        "Legal_Certification_Requirement":true,
        "Variant":"XYZ_Model_2025",
        "Verification_Method":"SIT",
        "Verification_Owner":"eCall Funcational Team"
    },
    {
        "Requirement_ID":"Req045",
        "Content":"eCall only mode: \nTCU shall perform mobile network registration only when the eCall is triggered.",
        "Header":"eCall only",
        "Qualification_Method":"eCall team supplier is responsible for providing the test result to Brand for approval",
        "Artifact_Type":"Functional Requirement",
        "System_Requirement_State":"Approved",
        "Assignee":"PQRS",
        "Review_Comment":"None",
        "Primary_Discipline":"SW",
        "Requirement_Type":"Functional",
        "System_Elements":"eCall",
        "ASIL_Rating":"A",
        "Cybersecurity":true,
        "Key_Requirement":true,
        "Legal_Certification_Requirement":true,
        "Variant":"XYZ_Model_2025",
        "Verification_Method":"SIT",
        "Verification_Owner":"eCall Funcational Team"
    },
    {
        "Requirement_ID":"Req046",
        "Content":"In case of eCall only mode MO eCall shall be as Req032 other MSD tranmission shall be as Req023 and MT eCall shall be as Req031",
        "Header":"eCall only",
        "Qualification_Method":"eCall team supplier is responsible for providing the test result to Brand for approval",
        "Artifact_Type":"Functional Requirement",
        "System_Requirement_State":"Approved",
        "Assignee":"PQRS",
        "Review_Comment":"None",
        "Primary_Discipline":"SW",
        "Requirement_Type":"Functional",
        "System_Elements":"eCall",
        "ASIL_Rating":"A",
        "Cybersecurity":true,
        "Key_Requirement":true,
        "Legal_Certification_Requirement":true,
        "Variant":"XYZ_Model_2025",
        "Verification_Method":"SIT",
        "Verification_Owner":"eCall Funcational Team"
    }
]